icenlpy/__init__.py
icenlpy/cli.py
icenlpy/iceparser.py
icenlpy/icetagger.py
icenlpy/resources/IceNLP/bat/demo/paramDefault.txt
icenlpy/resources/IceNLP/bat/demo/parse.out
icenlpy/resources/IceNLP/bat/demo/tagAndParse.bat
icenlpy/resources/IceNLP/bat/demo/tagAndParse.sh
icenlpy/resources/IceNLP/bat/demo/tagAndParseErrors.sh
icenlpy/resources/IceNLP/bat/demo/tagAndParseGUI.bat
icenlpy/resources/IceNLP/bat/demo/tagAndParseGUI.sh
icenlpy/resources/IceNLP/bat/demo/tagger.out
icenlpy/resources/IceNLP/bat/demo/test.txt
icenlpy/resources/IceNLP/bat/demo/test2.txt
icenlpy/resources/IceNLP/bat/demo/testErrors.txt
icenlpy/resources/IceNLP/bat/iceNER/iceNER.sh
icenlpy/resources/IceNLP/bat/iceNER/prufa.txt
icenlpy/resources/IceNLP/bat/icemorphy/icemorphy.bat
icenlpy/resources/IceNLP/bat/icemorphy/icemorphy.sh
icenlpy/resources/IceNLP/bat/icemorphy/paramAnalyze.txt
icenlpy/resources/IceNLP/bat/icemorphy/paramAnalyzeWithDicts.txt
icenlpy/resources/IceNLP/bat/icemorphy/paramFill.txt
icenlpy/resources/IceNLP/bat/icemorphy/paramFillWithDicts.txt
icenlpy/resources/IceNLP/bat/icemorphy/test.dict
icenlpy/resources/IceNLP/bat/icemorphy/test.txt
icenlpy/resources/IceNLP/bat/iceparser/200sent.txt
icenlpy/resources/IceNLP/bat/iceparser/200sent_func.gdc
icenlpy/resources/IceNLP/bat/iceparser/5.sent
icenlpy/resources/IceNLP/bat/iceparser/errorSearch/np_errors.sh
icenlpy/resources/IceNLP/bat/iceparser/errorSearch/pp_errors.sh
icenlpy/resources/IceNLP/bat/iceparser/errorSearch/vp_errors.sh
icenlpy/resources/IceNLP/bat/iceparser/iceparser.bat
icenlpy/resources/IceNLP/bat/iceparser/iceparser.sh
icenlpy/resources/IceNLP/bat/iceparser/iceparserOut.bat
icenlpy/resources/IceNLP/bat/iceparser/iceparserOut.sh
icenlpy/resources/IceNLP/bat/iceparser/iceparserOutOld.sh
icenlpy/resources/IceNLP/bat/iceparser/icestagger/corpora/README
icenlpy/resources/IceNLP/bat/iceparser/icestagger/icestagger.sh
icenlpy/resources/IceNLP/bat/iceparser/icestagger/sentences.txt
icenlpy-0.2.1.dist-info/LICENSE.txt
icenlpy-0.2.1.dist-info/METADATA
icenlpy-0.2.1.dist-info/WHEEL
icenlpy-0.2.1.dist-info/entry_points.txt
icenlpy-0.2.1.dist-info/RECORD
