Metadata-Version: 2.1
Name: icenlpy
Version: 0.2.1
Summary: A python wrapper for the IceNLP java library
Author: Hinrik Hafsteinsson
Author-email: hinrik.hafst@gmail.com
Requires-Python: >=3.8,<4.0
Classifier: Programming Language :: Python :: 3
Classifier: Programming Language :: Python :: 3.8
Classifier: Programming Language :: Python :: 3.9
Classifier: Programming Language :: Python :: 3.10
Classifier: Programming Language :: Python :: 3.11
Classifier: Programming Language :: Python :: 3.12
Requires-Dist: tomlkit (>=0.12.3,<0.13.0)
